fw_gear_validated_file_metadata_importer/__init__.py
fw_gear_validated_file_metadata_importer/derived.py
fw_gear_validated_file_metadata_importer/files/dicom.py
fw_gear_validated_file_metadata_importer/files/nifti.py
fw_gear_validated_file_metadata_importer/geometry.py
fw_gear_validated_file_metadata_importer/main.py
fw_gear_validated_file_metadata_importer/parser.py
fw_gear_validated_file_metadata_importer/transform.py
fw_gear_validated_file_metadata_importer/util.py
fw_gear_validated_file_metadata_importer-1.0.1.dist-info/LICENSE
fw_gear_validated_file_metadata_importer-1.0.1.dist-info/METADATA
fw_gear_validated_file_metadata_importer-1.0.1.dist-info/WHEEL
fw_gear_validated_file_metadata_importer-1.0.1.dist-info/RECORD
